{
  "timestamp": 1775595414,
  "seed": 1152557619,
  "matrix_fp": "f161992fd0a10c9b",
  "entropy": 7.69133,
  "depth": 0.0,
  "actions": [
    {
      "file": "lexeng/pipeline.py",
      "transform": "annotate",
      "message": "docs(index): pipeline \u2014 aabgh-aaavq-aacaw"
    },
    {
      "file": "lexeng/mutator.py",
      "transform": "refactor",
      "message": "refactor(engine): mutator \u2014 aaatx-aafyq-aadjt"
    },
    {
      "file": "lexeng/engine.py",
      "transform": "refactor",
      "message": "refactor(lattice): engine \u2014 aaahw-aaavs-aabyd"
    },
    {
      "file": "lexeng/corpus.py",
      "transform": "patch",
      "message": "fix(engine): corpus \u2014 aabfv-aacve-aabta"
    }
  ]
}